colour_cxf/__init__.py
colour_cxf/cxf3/__init__.py
colour_cxf/cxf3/brdfangle.py
colour_cxf/cxf3/color_adobe_rgb.py
colour_cxf/cxf3/color_cielab.py
colour_cxf/cxf3/color_cielch.py
colour_cxf/cxf3/color_cieluv.py
colour_cxf/cxf3/color_ciexy_y.py
colour_cxf/cxf3/color_ciexyz.py
colour_cxf/cxf3/color_cmyk.py
colour_cxf/cxf3/color_cmykplus_n.py
colour_cxf/cxf3/color_custom.py
colour_cxf/cxf3/color_density.py
colour_cxf/cxf3/color_difference_values.py
colour_cxf/cxf3/color_emissive_ciexy_y.py
colour_cxf/cxf3/color_emissive_ciexyz.py
colour_cxf/cxf3/color_hsl.py
colour_cxf/cxf3/color_html.py
colour_cxf/cxf3/color_notation.py
colour_cxf/cxf3/color_pantone_hexachrome.py
colour_cxf/cxf3/color_recipe.py
colour_cxf/cxf3/color_rgb.py
colour_cxf/cxf3/color_specification.py
colour_cxf/cxf3/color_specification_collection.py
colour_cxf/cxf3/color_srgb.py
colour_cxf/cxf3/color_values.py
colour_cxf/cxf3/colorant.py
colour_cxf/cxf3/creation_date.py
colour_cxf/cxf3/custom_attribute_string.py
colour_cxf/cxf3/custom_attribute_value.py
colour_cxf/cxf3/custom_color_space.py
colour_cxf/cxf3/custom_data_type.py
colour_cxf/cxf3/custom_delta_type.py
colour_cxf/cxf3/custom_illuminant.py
colour_cxf/cxf3/custom_resources.py
colour_cxf/cxf3/custom_spectrum.py
colour_cxf/cxf3/cx_f.py
colour_cxf/cxf3/de2000_type.py
colour_cxf/cxf3/de94_type.py
colour_cxf/cxf3/decmc_type.py
colour_cxf/cxf3/delta_cielab.py
colour_cxf/cxf3/delta_custom.py
colour_cxf/cxf3/device.py
colour_cxf/cxf3/device_class.py
colour_cxf/cxf3/device_color_values.py
colour_cxf/cxf3/device_filter.py
colour_cxf/cxf3/device_filter_type.py
colour_cxf/cxf3/device_illumination.py
colour_cxf/cxf3/eastm_table_type.py
colour_cxf/cxf3/edensity_filter_type.py
colour_cxf/cxf3/edensity_status_type.py
colour_cxf/cxf3/edevice_class_type.py
colour_cxf/cxf3/edevice_illumination_type.py
colour_cxf/cxf3/eemissive_mode_type.py
colour_cxf/cxf3/efilter_type.py
colour_cxf/cxf3/efinish_type.py
colour_cxf/cxf3/eilluminant_type.py
colour_cxf-0.1.1.dist-info/METADATA
colour_cxf-0.1.1.dist-info/WHEEL
colour_cxf-0.1.1.dist-info/licenses/LICENSE
colour_cxf-0.1.1.dist-info/RECORD
