Metadata-Version: 2.4
Name: colour-cxf
Version: 0.1.1
Summary: Library to parse and create CxF files.
Author-email: Colour Developers <colour-developers@colour-science.org>
Maintainer-email: Colour Developers <colour-developers@colour-science.org>
License: BSD-3-Clause
License-File: LICENSE
Keywords: CxF,color,color-science,color-space,color-spaces,colorspace,colorspaces,colour,colour-science,colour-space,colour-spaces,colourspace,colourspaces,python
Classifier: Development Status :: 3 - Alpha
Classifier: Environment :: Console
Classifier: Intended Audience :: Developers
Classifier: Intended Audience :: Science/Research
Classifier: License :: OSI Approved
Classifier: Natural Language :: English
Classifier: Operating System :: OS Independent
Classifier: Programming Language :: Python :: 3
Classifier: Topic :: Scientific/Engineering
Classifier: Topic :: Software Development
Requires-Python: <3.14,>=3.10
Requires-Dist: typing-extensions<5,>=4
Requires-Dist: xsdata>25.4
Provides-Extra: docs
Requires-Dist: biblib-simple; extra == 'docs'
Requires-Dist: lxml-asserts>=0.1.2; extra == 'docs'
Requires-Dist: pydata-sphinx-theme; extra == 'docs'
Requires-Dist: restructuredtext-lint; extra == 'docs'
Requires-Dist: sphinx; extra == 'docs'
Requires-Dist: sphinxcontrib-bibtex; extra == 'docs'
Requires-Dist: xsdata[cli]>=25.4; extra == 'docs'
